README.rst
setup.py
go_strong_auth_cli/__init__.py
go_strong_auth_cli/command_line.py
go_strong_auth_cli/pwdentry.py
go_strong_auth_cli.egg-info/PKG-INFO
go_strong_auth_cli.egg-info/SOURCES.txt
go_strong_auth_cli.egg-info/dependency_links.txt
go_strong_auth_cli.egg-info/entry_points.txt
go_strong_auth_cli.egg-info/not-zip-safe
go_strong_auth_cli.egg-info/requires.txt
go_strong_auth_cli.egg-info/top_level.txt