Metadata-Version: 1.0
Name: go-strong-auth-cli
Version: 0.2
Summary: CLI support for strong auth
Home-page: https://github.com/danielsomerfield/go-strong-auth-plugin.git
Author: Daniel Somerfield
Author-email: dsomerfi@thoughtworks.com
License: Apache License 2.0
Platform: UNKNOWN
